CHANGES.txt
MANIFEST.in
README.rst
setup.py
bin/imgoptimize
bin/imgresize
imgutil/__init__.py
imgutil/imgoptimize.py
imgutil/imgresize.py
imgutil.egg-info/PKG-INFO
imgutil.egg-info/SOURCES.txt
imgutil.egg-info/dependency_links.txt
imgutil.egg-info/requires.txt
imgutil.egg-info/top_level.txt
tests/__init__.py
tests/test_imgoptimize.py
tests/test_imgresize.py