Metadata-Version: 1.0
Name: imgutil
Version: 0.1.4
Summary: Image operation utilities.
Home-page: https://github.com/yu-liang-kono/imgutil
Author: yuliang
Author-email: yu.liang@thekono.com
License: UNKNOWN
Platform: UNKNOWN
